{"run_number": "1735993410790891", "step_name": "train_kmeans", "task_id": "3", "attempt_id": 0, "name": "mtx", "content_type": "gzip+pickle-v2", "type": "metaflow.artifact", "sha": "f76cd79d533208d8ada6c6c2bec4c5343aac2bc9", "ds_type": "local", "location": ":root:/home/fad/gitclonefolder/ums-L200220234.github.io/.metaflow", "flow_id": "KMeansFlow", "user_name": "fad", "tags": [], "system_tags": ["python_version:3.12.7", "user:fad", "metaflow_version:2.12.30", "runtime:dev"], "ts_epoch": 1735993427823}